analytics_logger_rest/__init__.py
analytics_logger_rest/analytics_logger_rest.py
analytics_logger_rest-1.0.1.dist-info/LICENSE
analytics_logger_rest-1.0.1.dist-info/METADATA
analytics_logger_rest-1.0.1.dist-info/WHEEL
analytics_logger_rest-1.0.1.dist-info/top_level.txt
analytics_logger_rest-1.0.1.dist-info/RECORD
